[{"RouteID":"A11","Name":"A11 - HUNTINGTON - PENTAGON","LineDescription":"Pentagon-Huntington"},{"RouteID":"A12","Name":"A12 - HUNTING POINT - BALLSTON","LineDescription":"Ballston-Hunting Point"},{"RouteID":"A1X","Name":"A1X - BRADDOCK RD - PENTAGON CITY","LineDescription":"Pentagon City-Braddock Rd"},{"RouteID":"A25","Name":"A25 - LANDMARK - PENTAGON","LineDescription":"Pentagon-S Fairlington-Landmark"},{"RouteID":"A27","Name":"A27 - VAN DORN - PENTAGON VIA EXPRESS","LineDescription":"Pentagon-Shirlington-Van Dorn St"},{"RouteID":"A28","Name":"A28 - LANDMARK - PENTAGON","LineDescription":"Pentagon-Holmes Run-Landmark"},{"RouteID":"A40","Name":"A40 - SKYLINE CITY-L'ENFANT PLZ","LineDescription":"Columbia Pike-National Landing"},{"RouteID":"A49","Name":"A49 - CULMORE - METRO CTR","LineDescription":"Columbia Pike-Metro Center"},{"RouteID":"A58","Name":"A58 - BALLSTON - FARRAGUT SQ","LineDescription":"Wilson Blvd-Farragut Sq"},{"RouteID":"A66","Name":"A66 - CULMORE - PENTAGON VIA EXPRESS","LineDescription":"Pentagon-Shirlington-Culmore"},{"RouteID":"A70","Name":"A70 - BALLSTON - POTOMAC YARD","LineDescription":"Glebe Rd"},{"RouteID":"A71","Name":"A71 - KING ST - BALLSTON","LineDescription":"Ballston-King St"},{"RouteID":"A76","Name":"A76 - MARK CTR - ROSSLYN","LineDescription":"Carlin Springs Rd"},{"RouteID":"A90","Name":"A90 - MARK CTR - PENTAGON HOV","LineDescription":"Pentagon-Mark Center"},{"RouteID":"C11","Name":"C11 - NATIONAL HARBOR - L'ENFANT PLZ","LineDescription":"S Capitol St"},{"RouteID":"C13","Name":"C13 - EASTOVER - ANACOSTIA","LineDescription":"MLK Av-Washington Highlands"},{"RouteID":"C15","Name":"C15 - SOUTHERN AV - ANACOSTIA","LineDescription":"MLK Av-Southern Av"},{"RouteID":"C17","Name":"C17 - EASTOVER - ANACOSTIA","LineDescription":"MLK Av-Bellevue"},{"RouteID":"C21","Name":"C21 - ANACOSTIA - MINNESOTA AV","LineDescription":"Alabama Av-Benning Rd"},{"RouteID":"C23","Name":"C23 - ANACOSTIA - DEANWOOD","LineDescription":"Alabama Av-Division Av"},{"RouteID":"C25","Name":"C25 - ANACOSTA - SKYLAND","LineDescription":"Pomeroy Rd-Skyland"},{"RouteID":"C26","Name":"C26 - ANACOSTIA - SKYLAND","LineDescription":"Stanton Rd-Skyland"},{"RouteID":"C27","Name":"C27 - SHEPHERD PKWY - NAYLOR RD","LineDescription":"Naylor Rd-Shepherd Pkwy"},{"RouteID":"C29","Name":"C29 - SOUTHERN AV - ANACOSTIA","LineDescription":"Anacostia-Southern Av"},{"RouteID":"C31","Name":"C31 - NAVY YARD - CAPITOL HTS","LineDescription":"Minnesota Av"},{"RouteID":"C33","Name":"C33 - MINNESOTA AV - EASTERN AV","LineDescription":"Sheriff Rd"},{"RouteID":"C35","Name":"C35 - FT DUPONT - DEANWOOD","LineDescription":"Deanwood-Mayfair-Fort Dupont"},{"RouteID":"C37","Name":"C37 - POTOMAC AV - MINNESOTA AV","LineDescription":"Lincoln Hts-Potomac Av"},{"RouteID":"C41","Name":"C41 - ANACOSTIA - MT RAINIER","LineDescription":"Bladensburg Rd"},{"RouteID":"C43","Name":"C43 - UNION STATION - CARVER TERRACE","LineDescription":"Maryland Av"},{"RouteID":"C51","Name":"C51 - ANACOSTIA - TENLEYTOWN","LineDescription":"U St-Anacostia"},{"RouteID":"C53","Name":"C53 - CONGRESS HTS - ADAMS MORGAN","LineDescription":"U St-Congress Hts"},{"RouteID":"C55","Name":"C55 - L'ENFANT PLZ - BUZZARD POINT","LineDescription":"Union Station-L'Enfant Plaza"},{"RouteID":"C57","Name":"C57 - U ST NW - CAPITOL HTS","LineDescription":"U St-Capitol Hts"},{"RouteID":"C61","Name":"C61 - TENLEYTOWN - COLUMBIA HTS","LineDescription":"Brookland-Tenleytown"},{"RouteID":"C63","Name":"C63 - WASH HOSPITAL CTR - DEANWOOD","LineDescription":"Deanwood-Wash Hospital Ctr"},{"RouteID":"C71","Name":"C71 - UNION STATION - FT TOTTEN","LineDescription":"18 St"},{"RouteID":"C75","Name":"C75 - PETWORTH - TAKOMA","LineDescription":"Takoma-Georgia Av"},{"RouteID":"C77","Name":"C77 - FT TOTTEN - TAKOMA","LineDescription":"Takoma-Fort Totten"},{"RouteID":"C81","Name":"C81 - SIBLEY HOSPITAL - FT TOTTEN","LineDescription":"Military Rd"},{"RouteID":"C83","Name":"C83 - FRIENDSHIP HTS - BARNABY WOODS","LineDescription":"Barnaby Woods-Friendship Hts"},{"RouteID":"C85","Name":"C85 - FOGGY BOTTOM - TENLEYTOWN","LineDescription":"Nebraska Av-Foggy Bottom"},{"RouteID":"C87","Name":"C87 - VAN NESS - SILVER SPG","LineDescription":"Silver Spring-Van Ness"},{"RouteID":"C91","Name":"C91 - GEORGETOWN - LEDROIT PK","LineDescription":"LeDroit Park-Georgetown"},{"RouteID":"D10","Name":"D10 - FOGGY BOTTOM - SOUTHERN AV","LineDescription":"Pennsylvania Av"},{"RouteID":"D1X","Name":"D1X - ARCHIVES - NAYLOR RD","LineDescription":"Pennsylvania Av Limited"},{"RouteID":"D20","Name":"D20 - PHELPS HS - MINNESOTA AV","LineDescription":"H St"},{"RouteID":"D24","Name":"D24 - MCPHERSON SQ - DEANWOOD","LineDescription":"E Capitol St"},{"RouteID":"D2X","Name":"D2X - GALLERY PL - CAPITOL HTS","LineDescription":"H St Limited"},{"RouteID":"D30","Name":"D30 - FEDERAL TRIANGLE - FT TOTTEN","LineDescription":"N Capitol St"},{"RouteID":"D32","Name":"D32 - GALLERY PL - FT LINCOLN","LineDescription":"Rhode Island Av-Fort Lincoln"},{"RouteID":"D34","Name":"D34 - METRO CTR - W HYATTSVL","LineDescription":"W Hyattsville-Edgewood-Metro Ctr"},{"RouteID":"D36","Name":"D36 - FRANKLIN SQ - WASH HOSP CTR","LineDescription":"K St-Ivy City"},{"RouteID":"D40","Name":"D40 - ARCHIVES - SILVER SPG","LineDescription":"7 St-Georgia Av"},{"RouteID":"D44","Name":"D44 - FEDERAL TRIANGLE - FT TOTTEN","LineDescription":"11 St"},{"RouteID":"D4X","Name":"D4X - ARCHIVES - SILVER SPG","LineDescription":"7 St-Georgia Av Limited"},{"RouteID":"D50","Name":"D50 - WATERFRONT - 14/COLORADO","LineDescription":"14 St"},{"RouteID":"D5X","Name":"D5X - 14/ASPEN - TAKOMA","LineDescription":"14 St Limited"},{"RouteID":"D60","Name":"D60 - FRANKLIN SQ - SILVER SPG","LineDescription":"16 St"},{"RouteID":"D6X","Name":"D6X - FEDERAL TRIANGLE - SILVER SPG","LineDescription":"16 St Limited"},{"RouteID":"D70","Name":"D70 - FARRAGUT SQ - CHEVY CHASE","LineDescription":"Connecticut Av-Chevy Chase"},{"RouteID":"D72","Name":"D72 - LAFAYETTE SQ - VAN NESS","LineDescription":"Connecticut Av-Mt Pleasant"},{"RouteID":"D74","Name":"D74 - POTOMAC PK - RHODE ISLD AV","LineDescription":"Rhode Island Av-Foggy Bottom"},{"RouteID":"D80","Name":"D80 - UNION STATION - FRIENDSHIP HTS","LineDescription":"Wisconsin Av-Union Station"},{"RouteID":"D82","Name":"D82 - POTOMAC PK - FRIENDSHIP HTS","LineDescription":"Wisconsin Av-Foggy Bottom"},{"RouteID":"D90","Name":"D90 - TENLEYTOWN - MT VERNON SQ","LineDescription":"Massachusetts Av-Tenleytown"},{"RouteID":"D94","Name":"D94 - SIBLEY HOSPITAL - GALLERY PL","LineDescription":"Gallery Place-Sibley Hospital"},{"RouteID":"D96","Name":"D96 - DUPONT CIR - BETHESDA","LineDescription":"Massachusetts Av-Bethesda"},{"RouteID":"F19","Name":"F19 - MT VERNON - POTOMAC PK","LineDescription":"Mt Vernon Estate Exp"},{"RouteID":"F1X","Name":"F1X - FT BELVOIR HOSP - KING ST","LineDescription":"Richmond Hwy"},{"RouteID":"F20","Name":"F20 - TYSONS - KING ST","LineDescription":"Leesburg Pike  "},{"RouteID":"F23","Name":"F23 - GEORGE MASON - KING ST","LineDescription":"Little River Tpk-George Mason"},{"RouteID":"F24","Name":"F24 - VIENNA - KING ST","LineDescription":"Little River Tpk-Vienna"},{"RouteID":"F26","Name":"F26 - NVCC ANNANDALE - E FALLS CHURCH","LineDescription":"E Falls Church-Annandale"},{"RouteID":"F28","Name":"F28 - KINGS PK W - PENTAGON","LineDescription":"Kings Park W Exp"},{"RouteID":"F29","Name":"F29 - GEORGE MASON - PENTAGON","LineDescription":"Braddock Rd"},{"RouteID":"F44","Name":"F44 - ANNANDALE - PENTAGON","LineDescription":"Columbia Pike-Pentagon"},{"RouteID":"F50","Name":"F50 - VIENNA - BALLSTON","LineDescription":"Washington Blvd"},{"RouteID":"F60","Name":"F60 - FAIR OAKS MALL - BALLSTON","LineDescription":"Arlington Blvd-Fair Oaks"},{"RouteID":"F61","Name":"F61 - VIENNA - BALLSTON","LineDescription":"Arlington Blvd-Jermantown Rd"},{"RouteID":"F62","Name":"F62 - DUNN LORRING - ROSSLYN","LineDescription":"Rosslyn-Arlington Blvd-Dunn Loring"},{"RouteID":"F81","Name":"F81 - BURKE CENTRE - PENTAGON","LineDescription":"Burke Centre Exp"},{"RouteID":"F83","Name":"F83 - ORANGE HUNT - PENTAGON","LineDescription":"Cardinal Forest Exp"},{"RouteID":"F85","Name":"F85 - ANNANDALE - PENTAGON","LineDescription":"Little River Tpk-Pentagon"},{"RouteID":"M12","Name":"M12 - WHEATON - TAKOMA LANGLEY","LineDescription":"University Blvd"},{"RouteID":"M20","Name":"M20 - SILVER SPG - WHEATON","LineDescription":"Wheaton-Silver Spring"},{"RouteID":"M22","Name":"M22 - BETHESDA - OLNEY","LineDescription":"Olney-Bethesda"},{"RouteID":"M42","Name":"M42 - CHERRY HILL - COLLEGE PK","LineDescription":"Randolph Rd-College Park"},{"RouteID":"M44","Name":"M44 - N BETHESDA - PLUM ORCHARD","LineDescription":"Randolph Rd-Hyattsville Crossing"},{"RouteID":"M52","Name":"M52 - SILVER SPG - BURTONSVILLE","LineDescription":"Colesville Rd-Burtonsville"},{"RouteID":"M54","Name":"M54 - SILVER SPG - GREENCASTLE","LineDescription":"Colesville Rd-Greencastle"},{"RouteID":"M60","Name":"M60 - FT TOTTEN - PLUM ORCHARD","LineDescription":"New Hampshire Av"},{"RouteID":"M6X","Name":"M6X - FT TOTTEN - FDA","LineDescription":"New Hampshire Av Limited"},{"RouteID":"M70","Name":"M70 - MONTGOMERY MALL - SILVER SPG","LineDescription":"East West Hwy"},{"RouteID":"M82","Name":"M82 - FRIENDSHIP HTS - ROCKVILLE","LineDescription":"River Rd-Falls Rd"},{"RouteID":"P10","Name":"P10 - RHODE ISLD AV - COLLEGE PK","LineDescription":"Baltimore Av"},{"RouteID":"P12","Name":"P12 - GREENBELT - LAUREL","LineDescription":"Laurel-Greenbelt"},{"RouteID":"P14","Name":"P14 - DEANWOOD - GREENBELT","LineDescription":"Kenilworth Av"},{"RouteID":"P15","Name":"P15 - FT TOTTEN - ADELPHI","LineDescription":"Riggs Rd-Adelphi"},{"RouteID":"P16","Name":"P16 - FT TOTTEN - PLUM ORCHARD","LineDescription":"Riggs Rd-White Oak"},{"RouteID":"P1X","Name":"P1X - RHODE ISLD AV - IKEA","LineDescription":"Baltimore Av Limited"},{"RouteID":"P20","Name":"P20 - NEW CRLTN - GREENBELT","LineDescription":"Greenbelt Rd-New Carrollton"},{"RouteID":"P21","Name":"P21 - NEW CRLTN - GREENBELT","LineDescription":"Hanover Pkwy-New Carrollton"},{"RouteID":"P24","Name":"P24 - NEW CRLTN - MISSION DR","LineDescription":"Good Luck Rd"},{"RouteID":"P30","Name":"P30 - SILVER SPG - NEW CRLTN","LineDescription":"New Carrollton-Silver Spring"},{"RouteID":"P31","Name":"P31 - COLLEGE PK - NEW CRLTN","LineDescription":"New Carrollton-Takoma Langley"},{"RouteID":"P32","Name":"P32 - FT TOTTEN - GREENBELT","LineDescription":"Greenbelt-Fort Totten"},{"RouteID":"P33","Name":"P33 - BROOKLAND - HIGHVIEW","LineDescription":"Queens Chapel Rd"},{"RouteID":"P35","Name":"P35 - FT TOTTEN - NEW CRLTN","LineDescription":"New Carrollton-Fort Totten"},{"RouteID":"P40","Name":"P40 - BLADENSBURG HS - NEW CRLTN","LineDescription":"Annapolis Rd"},{"RouteID":"P41","Name":"P41 - CAPITAL PLZ - LARGO","LineDescription":"Landover Rd"},{"RouteID":"P42","Name":"P42 - FT LINCOLN - NEW CRLTN","LineDescription":"Chillum Rd-New Carrollton"},{"RouteID":"P60","Name":"P60 - SUITLAND - NEW CRLTN","LineDescription":"MLK Hwy-Suitland"},{"RouteID":"P61","Name":"P61 - SUITLAND - NEW CRLTN","LineDescription":"Glenarden-Suitland"},{"RouteID":"P62","Name":"P62 - BRANCH AV - DEANWOOD","LineDescription":"Deanwood-Branch Av"},{"RouteID":"P63","Name":"P63 - NAYLOR RD - LARGO","LineDescription":"Central Av-Naylor Rd"},{"RouteID":"P66","Name":"P66 - SUITLAND - FORESTVILLE","LineDescription":"Forestville-Suitland"},{"RouteID":"P72","Name":"P72 - LARGO - BOWIE P+R","LineDescription":"Central Av-Bowie"},{"RouteID":"P73","Name":"P73 - LARGO - TRADE ZONE AV","LineDescription":"Central Av-Trade Zone"},{"RouteID":"P87","Name":"P87 - OXON HILL P+R - SUITLAND","LineDescription":"Brinkley Rd"},{"RouteID":"P90","Name":"P90 - KING ST - NATIONAL HARBOR","LineDescription":"St Barnabas Rd"},{"RouteID":"P93","Name":"P93 - EASTOVER - SUITLAND","LineDescription":"Birchwood - Suitland"},{"RouteID":"P94","Name":"P94 - NATIONAL HARBOR - SUITLAND","LineDescription":"National Harbor - Suitland"},{"RouteID":"P96","Name":"P96 - OXON HILL P+R - SUITLAND","LineDescription":"Suitland-Oxon Hill"},{"RouteID":"P97","Name":"P97 - FT WASHINGTON - SOUTHERN AV","LineDescription":"Southern Av-Ft Washington"}]